README.rst
setup.cfg
setup.py
bookworm/__init__.py
bookworm/api.py
bookworm/version.py
bookworm.egg-info/PKG-INFO
bookworm.egg-info/SOURCES.txt
bookworm.egg-info/dependency_links.txt
bookworm.egg-info/requires.txt
bookworm.egg-info/top_level.txt