Metadata-Version: 1.1
Name: bookworm
Version: 0.1.5
Summary: Text analysis api
Home-page: https://github.com/crawlica/bookworm-client
Author: Crawlica
Author-email: tech@crawlica.com
License: Apache 2.0
Download-URL: https://github.com/crawlica/bookworm-client/tarball/0.1.5
Platform: POSIX
